pympg/__init__.py
pympg/cli.py
pympg/gen/apache.py
pympg/gen/main.py
pympg/gen/nginx.py
pympg-0.0.6.dist-info/entry_points.txt
pympg-0.0.6.dist-info/LICENSE
pympg-0.0.6.dist-info/WHEEL
pympg-0.0.6.dist-info/METADATA
pympg-0.0.6.dist-info/RECORD
