Metadata-Version: 2.1
Name: pympg
Version: 0.0.6
Summary: Command-line multipurpose generator.
License: MIT
Author: Theo Paris
Author-email: theoparisdesigns@gmail.com
Requires-Python: >=3.6,<3.10
Classifier: License :: OSI Approved :: MIT License
Classifier: Programming Language :: Python :: 3
Classifier: Programming Language :: Python :: 3.6
Classifier: Programming Language :: Python :: 3.7
Classifier: Programming Language :: Python :: 3.8
Classifier: Programming Language :: Python :: 3.9
Requires-Dist: questionary (>=1.9.0)
